pyloco/__init__.py
pyloco/__main__.py
pyloco/base.py
pyloco/error.py
pyloco/grouptask.py
pyloco/helptask.py
pyloco/main.py
pyloco/manage.py
pyloco/mgmttask.py
pyloco/parse.py
pyloco/plxtask.py
pyloco/plztask.py
pyloco/proxy.py
pyloco/stdtask.py
pyloco/task.py
pyloco/test.py
pyloco/util.py
pyloco/webserver.py
pyloco/websocket.py
pyloco-0.0.138.dist-info/LICENSE
pyloco-0.0.138.dist-info/METADATA
pyloco-0.0.138.dist-info/WHEEL
pyloco-0.0.138.dist-info/entry_points.txt
pyloco-0.0.138.dist-info/top_level.txt
pyloco-0.0.138.dist-info/RECORD
