Metadata-Version: 2.1
Name: pyloco
Version: 0.0.138
Summary: Python Microapplication Launcher
Home-page: https://github.com/grnydawn/pyloco
Author: Youngsung Kim
Author-email: grnydawn@gmail.com
License: UNKNOWN
Project-URL: Bug Reports, https://github.com/grnydawn/pyloco/issues
Project-URL: Source, https://github.com/grnydawn/pyloco
Keywords: task
Platform: UNKNOWN
Classifier: Development Status :: 3 - Alpha
Classifier: Intended Audience :: Developers
Classifier: Topic :: Software Development :: Build Tools
Classifier: License :: OSI Approved :: Apache Software License
Classifier: Programming Language :: Python :: 2
Classifier: Programming Language :: Python :: 2.7
Classifier: Programming Language :: Python :: 3
Classifier: Programming Language :: Python :: 3.5
Classifier: Programming Language :: Python :: 3.6
Classifier: Programming Language :: Python :: 3.7
Requires-Dist: ushlex
Requires-Dist: websocket-client
Requires-Dist: twine
Requires-Dist: typing
Requires-Dist: SimpleWebSocketServer
